{"2008":{"SC Ganguly":{"runs":349,"balls":157},"BB McCullum":{"runs":188,"balls":64},"RT Ponting":{"runs":39,"balls":27},"DJ Hussey":{"runs":319,"balls":158},"Mohammad Hafeez":{"runs":64,"balls":33},"R Dravid":{"runs":371,"balls":195},"W Jaffer":{"runs":115,"balls":58},"V Kohli":{"runs":165,"balls":86},"JH Kallis":{"runs":199,"balls":106},"CL White":{"runs":114,"balls":65},"MV Boucher":{"runs":225,"balls":113},"B Akhil":{"runs":46,"balls":18},"AA Noffke":{"runs":9,"balls":6},"P Kumar":{"runs":112,"balls":47},"Z Khan":{"runs":34,"balls":21},"SB Joshi":{"runs":6,"balls":6},"PA Patel":{"runs":302,"balls":149},"ML Hayden":{"runs":189,"balls":82},"MEK Hussey":{"runs":168,"balls":69},"MS Dhoni":{"runs":414,"balls":195},"SK Raina":{"runs":421,"balls":206},"JDP Oram":{"runs":18,"balls":9},"S Badrinath":{"runs":192,"balls":79},"K Goel":{"runs":76,"balls":32},"JR Hopes":{"runs":221,"balls":91},"KC Sangakkara":{"runs":320,"balls":138},"Yuvraj Singh":{"runs":299,"balls":123},"SM Katich":{"runs":96,"balls":43},"IK Pathan":{"runs":131,"balls":64},"T Kohli":{"runs":10,"balls":5},"YK Pathan":{"runs":435,"balls":164},"SR Watson":{"runs":472,"balls":208},"M Kaif":{"runs":176,"balls":89},"DS Lehmann":{"runs":18,"balls":9},"RA Jadeja":{"runs":135,"balls":62},"M Rawat":{"runs":34,"balls":18},"D Salunkhe":{"runs":33,"balls":16},"SK Warne":{"runs":70,"balls":35},"SK Trivedi":{"runs":5,"balls":5},"G Gambhir":{"runs":534,"balls":260},"V Sehwag":{"runs":406,"balls":152},"S Dhawan":{"runs":340,"balls":174},"L Ronchi":{"runs":34,"balls":11},"ST Jayasuriya":{"runs":514,"balls":171},"DJ Thornely":{"runs":39,"balls":23},"RV Uthappa":{"runs":320,"balls":158},"PR Shah":{"runs":34,"balls":19},"AM Nayar":{"runs":206,"balls":100},"SM Pollock":{"runs":147,"balls":69},"Harbhajan Singh":{"runs":30,"balls":11},"S Chanderpaul":{"runs":25,"balls":13},"LRPL Taylor":{"runs":149,"balls":57},"AC Gilchrist":{"runs":436,"balls":175},"Y Venugopal Rao":{"runs":288,"balls":130},"VVS Laxman":{"runs":155,"balls":81},"A Symonds":{"runs":161,"balls":64},"RG Sharma":{"runs":404,"balls":176},"SB Styris":{"runs":112,"balls":72},"AS Yadav":{"runs":49,"balls":22},"SB Bangar":{"runs":47,"balls":28},"WPUJC Vaas":{"runs":21,"balls":11},"RP Singh":{"runs":27,"balls":16},"WP Saha":{"runs":159,"balls":73},"LR Shukla":{"runs":163,"balls":83},"DPMD Jayawardene":{"runs":179,"balls":86},"S Sohal":{"runs":4,"balls":3},"B Lee":{"runs":17,"balls":6},"PP Chawla":{"runs":90,"balls":36},"WA Mota":{"runs":26,"balls":18},"Kamran Akmal":{"runs":128,"balls":45},"Shahid Afridi":{"runs":81,"balls":26},"DJ Bravo":{"runs":178,"balls":84},"MA Khote":{"runs":24,"balls":12},"A Nehra":{"runs":3,"balls":3},"GC Smith":{"runs":441,"balls":217},"Pankaj Singh":{"runs":5,"balls":4},"RR Sarwan":{"runs":73,"balls":44},"S Sreesanth":{"runs":0,"balls":0},"VRV Singh":{"runs":4,"balls":1},"SS Tiwary":{"runs":26,"balls":12},"DS Kulkarni":{"runs":2,"balls":2},"R Vinay Kumar":{"runs":25,"balls":12},"AB Agarkar":{"runs":54,"balls":25},"M Kartik":{"runs":30,"balls":18},"I Sharma":{"runs":11,"balls":6},"AM Rahane":{"runs":4,"balls":1},"Shoaib Malik":{"runs":52,"balls":33},"MK Tiwary":{"runs":104,"balls":54},"KD Karthik":{"runs":145,"balls":73},"R Bhatia":{"runs":34,"balls":17},"MF Maharoof":{"runs":125,"balls":52},"VY Mahesh":{"runs":15,"balls":13},"TM Srivastava":{"runs":8,"balls":6},"B Chipli":{"runs":20,"balls":11},"DW Steyn":{"runs":2,"balls":2},"DB Das":{"runs":103,"balls":48},"MK Pandey":{"runs":3,"balls":3},"HH Gibbs":{"runs":167,"balls":69},"DNT Zoysa":{"runs":11,"balls":6},"D Kalyankrishna":{"runs":3,"balls":3},"SE Marsh":{"runs":616,"balls":281},"SA Asnodkar":{"runs":311,"balls":140},"Sohail Tanvir":{"runs":36,"balls":20},"Salman Butt":{"runs":193,"balls":86},"BJ Hodge":{"runs":12,"balls":6},"Umar Gul":{"runs":39,"balls":11},"AB Dinda":{"runs":2,"balls":2},"SP Fleming":{"runs":196,"balls":85},"S Vidyut":{"runs":145,"balls":60},"JA Morkel":{"runs":241,"balls":105},"AB de Villiers":{"runs":95,"balls":59},"LPC Silva":{"runs":40,"balls":17},"DB Ravi Teja":{"runs":109,"balls":51},"Misbah-ul-Haq":{"runs":117,"balls":51},"YV Takawale":{"runs":70,"balls":30},"RR Raje":{"runs":8,"balls":5},"PJ Sangwan":{"runs":2,"balls":1},"Mohammad Asif":{"runs":3,"balls":3},"GD McGrath":{"runs":4,"balls":1},"Joginder Sharma":{"runs":16,"balls":8},"MS Gony":{"runs":35,"balls":13},"M Muralitharan":{"runs":0,"balls":0},"M Ntini":{"runs":11,"balls":4},"DT Patil":{"runs":13,"balls":8},"A Kumble":{"runs":13,"balls":9},"S Anirudha":{"runs":1,"balls":1},"MM Patel":{"runs":0,"balls":0},"CK Kapugedera":{"runs":16,"balls":14},"A Chopra":{"runs":42,"balls":25},"T Taibu":{"runs":31,"balls":17},"J Arunkumar":{"runs":23,"balls":8},"PP Ojha":{"runs":2,"balls":2},"SP Goswami":{"runs":82,"balls":44},"SR Tendulkar":{"runs":188,"balls":92},"U Kaul":{"runs":0,"balls":0},"TM Dilshan":{"runs":104,"balls":45},"A Mishra":{"runs":37,"balls":26},"AD Mascarenhas":{"runs":9,"balls":4},"Niraj Patel":{"runs":103,"balls":50},"LA Pomersbach":{"runs":152,"balls":65},"Iqbal Abdulla":{"runs":1,"balls":1},"Younis Khan":{"runs":3,"balls":3},"PM Sarvesh Kumar":{"runs":1,"balls":1},"DP Vijaykumar":{"runs":1,"balls":1},"Shoaib Akhtar":{"runs":2,"balls":2},"Abdur Razzak":{"runs":0,"balls":0},"H Das":{"runs":2,"balls":2},"DR Smith":{"runs":45,"balls":22},"SD Chitnis":{"runs":18,"balls":9},"CRD Fernando":{"runs":2,"balls":1},"VS Yeligati":{"runs":2,"balls":1},"L Balaji":{"runs":0,"balls":0},"A Mukund":{"runs":0,"balls":0},"RR Powar":{"runs":28,"balls":11}},"2009":{"ST Jayasuriya":{"runs":221,"balls":96},"SR Tendulkar":{"runs":364,"balls":180},"S Dhawan":{"runs":40,"balls":27},"JP Duminy":{"runs":372,"balls":211},"DJ Bravo":{"runs":218,"balls":112},"AM Nayar":{"runs":193,"balls":97},"Harbhajan Singh":{"runs":84,"balls":36},"Z Khan":{"runs":8,"balls":8},"PA Patel":{"runs":142,"balls":69},"SK Raina":{"runs":434,"balls":197},"ML Hayden":{"runs":572,"balls":248},"A Flintoff":{"runs":62,"balls":33},"MS Dhoni":{"runs":332,"balls":195},"JDP Oram":{"runs":88,"balls":51},"S Badrinath":{"runs":177,"balls":88},"Joginder Sharma":{"runs":20,"balls":12},"T Thushara":{"runs":2,"balls":2},"JD Ryder":{"runs":56,"balls":23},"LRPL Taylor":{"runs":280,"balls":126},"KP Pietersen":{"runs":93,"balls":47},"RV Uthappa":{"runs":175,"balls":92},"R Dravid":{"runs":271,"balls":149},"V Kohli":{"runs":246,"balls":127},"B Akhil":{"runs":17,"balls":7},"P Kumar":{"runs":65,"balls":27},"R Vinay Kumar":{"runs":47,"balls":24},"GC Smith":{"runs":212,"balls":114},"SA Asnodkar":{"runs":98,"balls":41},"Niraj Patel":{"runs":18,"balls":13},"T Henderson":{"runs":11,"balls":5},"YK Pathan":{"runs":261,"balls":100},"AD Mascarenhas":{"runs":39,"balls":24},"RA Jadeja":{"runs":295,"balls":174},"SK Warne":{"runs":108,"balls":64},"M Rawat":{"runs":16,"balls":13},"MM Patel":{"runs":33,"balls":18},"Kamran Khan":{"runs":3,"balls":2},"RS Bopara":{"runs":138,"balls":74},"K Goel":{"runs":124,"balls":67},"KC Sangakkara":{"runs":332,"balls":194},"Yuvraj Singh":{"runs":340,"balls":170},"DPMD Jayawardene":{"runs":219,"balls":119},"IK Pathan":{"runs":196,"balls":97},"G Gambhir":{"runs":286,"balls":155},"V Sehwag":{"runs":198,"balls":81},"BB McCullum":{"runs":286,"balls":129},"CH Gayle":{"runs":184,"balls":74},"SC Ganguly":{"runs":189,"balls":107},"BJ Hodge":{"runs":365,"balls":192},"A Chopra":{"runs":11,"balls":5},"LR Shukla":{"runs":83,"balls":43},"MC Henriques":{"runs":38,"balls":21},"AB Agarkar":{"runs":66,"balls":37},"M Kartik":{"runs":21,"balls":18},"I Sharma":{"runs":16,"balls":7},"AB Dinda":{"runs":2,"balls":1},"AC Gilchrist":{"runs":495,"balls":175},"HH Gibbs":{"runs":371,"balls":189},"VVS Laxman":{"runs":19,"balls":11},"RG Sharma":{"runs":362,"balls":191},"JA Morkel":{"runs":97,"balls":51},"JH Kallis":{"runs":361,"balls":181},"R Bishnoi":{"runs":19,"balls":6},"DW Steyn":{"runs":0,"balls":0},"A Kumble":{"runs":16,"balls":10},"T Kohli":{"runs":1,"balls":1},"PP Chawla":{"runs":31,"balls":18},"SB Styris":{"runs":14,"balls":7},"Y Venugopal Rao":{"runs":124,"balls":78},"DB Ravi Teja":{"runs":65,"balls":38},"FH Edwards":{"runs":4,"balls":2},"KV Sharma":{"runs":1,"balls":1},"AB de Villiers":{"runs":465,"balls":247},"TM Dilshan":{"runs":418,"balls":201},"KD Karthik":{"runs":288,"balls":156},"MK Tiwary":{"runs":9,"balls":6},"MS Gony":{"runs":13,"balls":3},"M Muralitharan":{"runs":8,"balls":5},"PC Valthaty":{"runs":6,"balls":3},"RJ Quiney":{"runs":103,"balls":48},"AS Raut":{"runs":78,"balls":40},"SB Bangar":{"runs":2,"balls":2},"Yashpal Singh":{"runs":47,"balls":28},"Pankaj Singh":{"runs":1,"balls":1},"DR Smith":{"runs":215,"balls":90},"RP Singh":{"runs":8,"balls":7},"PP Ojha":{"runs":1,"balls":1},"PR Shah":{"runs":53,"balls":26},"MV Boucher":{"runs":150,"balls":77},"M Manhas":{"runs":75,"balls":38},"WA Mota":{"runs":30,"balls":28},"AA Bilakhia":{"runs":67,"balls":43},"SS Tiwary":{"runs":13,"balls":9},"AN Ghosh":{"runs":7,"balls":3},"BAW Mendis":{"runs":0,"balls":0},"DL Vettori":{"runs":34,"balls":21},"A Mishra":{"runs":26,"balls":9},"PJ Sangwan":{"runs":6,"balls":5},"MN van Wyk":{"runs":167,"balls":91},"WP Saha":{"runs":72,"balls":35},"SP Goswami":{"runs":53,"balls":30},"RE van der Merwe":{"runs":122,"balls":52},"MK Pandey":{"runs":168,"balls":79},"RR Powar":{"runs":23,"balls":15},"TL Suman":{"runs":237,"balls":117},"Shoaib Ahmed":{"runs":1,"balls":1},"SK Trivedi":{"runs":9,"balls":8},"GR Napier":{"runs":15,"balls":9},"AM Rahane":{"runs":144,"balls":81},"KP Appanna":{"runs":0,"balls":0},"SM Katich":{"runs":145,"balls":63},"TM Srivastava":{"runs":0,"balls":0},"LA Carseldine":{"runs":81,"balls":40},"NV Ojha":{"runs":168,"balls":71},"SM Harwood":{"runs":9,"balls":7},"M Vijay":{"runs":60,"balls":34},"SB Jakati":{"runs":20,"balls":10},"L Balaji":{"runs":4,"balls":3},"DA Warner":{"runs":163,"balls":78},"R Bhatia":{"runs":8,"balls":5},"S Sohal":{"runs":115,"balls":42},"W Jaffer":{"runs":15,"balls":7},"RJ Harris":{"runs":21,"balls":12},"S Sreesanth":{"runs":5,"balls":2},"RR Raje":{"runs":12,"balls":7},"DS Kulkarni":{"runs":9,"balls":9},"D du Preez":{"runs":10,"balls":8},"L Ronchi":{"runs":0,"balls":0},"A Symonds":{"runs":249,"balls":116},"B Lee":{"runs":28,"balls":16},"WPUJC Vaas":{"runs":30,"balls":18},"M Morkel":{"runs":8,"balls":4},"DJ Hussey":{"runs":98,"balls":39},"AD Mathews":{"runs":16,"balls":10},"LA Pomersbach":{"runs":41,"balls":24},"SD Chitnis":{"runs":6,"balls":3},"J Botha":{"runs":47,"balls":27},"YV Takawale":{"runs":18,"balls":10},"C Nanda":{"runs":0,"balls":0},"SL Malinga":{"runs":0,"balls":0},"MF Maharoof":{"runs":21,"balls":14},"A Nehra":{"runs":1,"balls":1},"Mashrafe Mortaza":{"runs":2,"balls":1},"A Singh":{"runs":1,"balls":1},"GJ Bailey":{"runs":45,"balls":22},"AB McDonald":{"runs":3,"balls":3},"Y Nagar":{"runs":20,"balls":13},"SS Shaikh":{"runs":6,"balls":3},"R Ashwin":{"runs":8,"balls":5},"Mohammad Ashraful":{"runs":2,"balls":2}},"2010":{"MK Tiwary":{"runs":237,"balls":129},"SC Ganguly":{"runs":493,"balls":224},"CA Pujara":{"runs":122,"balls":63},"BJ Hodge":{"runs":99,"balls":54},"OA Shah":{"runs":115,"balls":63},"AD Mathews":{"runs":233,"balls":119},"AC Gilchrist":{"runs":289,"balls":107},"VVS Laxman":{"runs":64,"balls":35},"HH Gibbs":{"runs":267,"balls":129},"A Symonds":{"runs":429,"balls":211},"RG Sharma":{"runs":404,"balls":202},"Anirudh Singh":{"runs":63,"balls":35},"TL Suman":{"runs":307,"balls":157},"WPUJC Vaas":{"runs":30,"balls":20},"Jaskaran Singh":{"runs":8,"balls":6},"ST Jayasuriya":{"runs":33,"balls":14},"SR Tendulkar":{"runs":618,"balls":305},"AP Tare":{"runs":50,"balls":16},"SS Tiwary":{"runs":419,"balls":214},"AT Rayudu":{"runs":356,"balls":171},"R Sathish":{"runs":112,"balls":64},"Harbhajan Singh":{"runs":105,"balls":40},"R McLaren":{"runs":66,"balls":40},"GC Smith":{"runs":44,"balls":20},"NV Ojha":{"runs":377,"balls":164},"AA Jhunjhunwala":{"runs":183,"balls":102},"YK Pathan":{"runs":333,"balls":134},"P Dogra":{"runs":107,"balls":61},"AD Mascarenhas":{"runs":12,"balls":9},"A Uniyal":{"runs":4,"balls":4},"SK Warne":{"runs":10,"balls":8},"RS Bopara":{"runs":248,"balls":136},"MS Bisla":{"runs":218,"balls":91},"KC Sangakkara":{"runs":357,"balls":174},"Yuvraj Singh":{"runs":259,"balls":116},"DPMD Jayawardene":{"runs":445,"balls":201},"IK Pathan":{"runs":276,"balls":141},"M Kaif":{"runs":28,"balls":20},"PP Chawla":{"runs":62,"balls":36},"RR Powar":{"runs":5,"balls":3},"S Sreesanth":{"runs":27,"balls":10},"YA Abdulla":{"runs":0,"balls":0},"G Gambhir":{"runs":277,"balls":142},"V Sehwag":{"runs":356,"balls":136},"TM Dilshan":{"runs":44,"balls":25},"AB de Villiers":{"runs":111,"balls":76},"KD Karthik":{"runs":278,"balls":155},"M Manhas":{"runs":157,"balls":103},"MF Maharoof":{"runs":31,"balls":14},"JH Kallis":{"runs":572,"balls":298},"SP Goswami":{"runs":8,"balls":2},"MK Pandey":{"runs":249,"balls":118},"V Kohli":{"runs":307,"balls":155},"EJG Morgan":{"runs":35,"balls":21},"R Dravid":{"runs":256,"balls":128},"RV Uthappa":{"runs":374,"balls":153},"RE van der Merwe":{"runs":1,"balls":1},"P Kumar":{"runs":4,"balls":3},"M Vijay":{"runs":458,"balls":189},"ML Hayden":{"runs":346,"balls":142},"SK Raina":{"runs":528,"balls":251},"S Badrinath":{"runs":356,"balls":190},"JM Kemp":{"runs":26,"balls":14},"MS Dhoni":{"runs":287,"balls":149},"JA Morkel":{"runs":199,"balls":92},"R Ashwin":{"runs":30,"balls":23},"L Balaji":{"runs":18,"balls":10},"M Muralitharan":{"runs":1,"balls":1},"S Tyagi":{"runs":3,"balls":3},"SA Asnodkar":{"runs":5,"balls":2},"WP Saha":{"runs":67,"balls":32},"LR Shukla":{"runs":36,"balls":16},"RS Gavaskar":{"runs":2,"balls":2},"SE Bond":{"runs":1,"balls":1},"M Kartik":{"runs":22,"balls":13},"I Sharma":{"runs":6,"balls":6},"KA Pollard":{"runs":273,"balls":100},"DJ Bravo":{"runs":61,"balls":28},"A Mishra":{"runs":39,"balls":34},"PJ Sangwan":{"runs":10,"balls":9},"S Ladda":{"runs":0,"balls":0},"DP Nannes":{"runs":4,"balls":4},"MJ Lumb":{"runs":278,"balls":102},"DR Martyn":{"runs":19,"balls":16},"S Narwal":{"runs":14,"balls":7},"M Morkel":{"runs":9,"balls":5},"MM Patel":{"runs":4,"balls":3},"SK Trivedi":{"runs":20,"balls":6},"DA Warner":{"runs":282,"balls":120},"R Bhatia":{"runs":24,"balls":10},"PA Patel":{"runs":72,"balls":42},"RP Singh":{"runs":9,"balls":6},"AB Barath":{"runs":42,"balls":21},"Bipul Sharma":{"runs":9,"balls":6},"FY Fazal":{"runs":164,"balls":96},"AC Voges":{"runs":181,"balls":99},"Z Khan":{"runs":24,"balls":8},"MD Mishra":{"runs":166,"balls":74},"Y Venugopal Rao":{"runs":34,"balls":20},"MC Henriques":{"runs":11,"balls":4},"Y Nagar":{"runs":1,"balls":1},"UT Yadav":{"runs":3,"balls":3},"J Theron":{"runs":2,"balls":2},"MS Gony":{"runs":2,"balls":2},"CH Gayle":{"runs":292,"balls":115},"S Dhawan":{"runs":191,"balls":95},"MV Boucher":{"runs":13,"balls":8},"GJ Bailey":{"runs":18,"balls":11},"SJ Srivastava":{"runs":1,"balls":1},"R Sharma":{"runs":29,"balls":11},"Mandeep Singh":{"runs":4,"balls":1},"DJ Hussey":{"runs":94,"balls":52},"K Goel":{"runs":18,"balls":10},"B Lee":{"runs":11,"balls":7},"KM Jadhav":{"runs":76,"balls":39},"AB McDonald":{"runs":65,"balls":38},"R Vinay Kumar":{"runs":27,"balls":20},"DW Steyn":{"runs":13,"balls":7},"A Kumble":{"runs":6,"balls":6},"SW Tait":{"runs":12,"balls":7},"KB Arun Karthik":{"runs":3,"balls":3},"T Thushara":{"runs":10,"balls":7},"KAJ Roach":{"runs":10,"balls":6},"PD Collingwood":{"runs":203,"balls":99},"AB Agarkar":{"runs":40,"balls":23},"CK Langeveldt":{"runs":0,"balls":0},"SE Marsh":{"runs":147,"balls":70},"VS Malik":{"runs":6,"balls":3},"KP Pietersen":{"runs":236,"balls":109},"CL White":{"runs":48,"balls":22},"SR Watson":{"runs":185,"balls":76},"AS Raut":{"runs":56,"balls":29},"RJ Harris":{"runs":45,"balls":24},"PP Ojha":{"runs":3,"balls":2},"DL Vettori":{"runs":33,"balls":19},"LRPL Taylor":{"runs":88,"balls":49},"A Mithun":{"runs":5,"balls":2},"KP Appanna":{"runs":2,"balls":2},"AP Dole":{"runs":34,"balls":16},"DR Smith":{"runs":22,"balls":12},"AA Bilakhia":{"runs":2,"balls":2},"MEK Hussey":{"runs":37,"balls":25},"AN Ahmed":{"runs":4,"balls":3},"BB McCullum":{"runs":114,"balls":57},"JP Duminy":{"runs":157,"balls":86},"RS Sodhi":{"runs":4,"balls":1},"DE Bollinger":{"runs":18,"balls":9},"AB Dinda":{"runs":0,"balls":0},"BAW Mendis":{"runs":1,"balls":1},"S Sriram":{"runs":27,"balls":17},"A Nehra":{"runs":23,"balls":12},"B Sumanth":{"runs":35,"balls":23},"C Madan":{"runs":15,"balls":6},"Iqbal Abdulla":{"runs":0,"balls":0},"AG Paunikar":{"runs":0,"balls":0},"MR Marsh":{"runs":28,"balls":19},"AM Nayar":{"runs":58,"balls":32},"Pankaj Singh":{"runs":1,"balls":1},"AJ Finch":{"runs":21,"balls":14},"STR Binny":{"runs":8,"balls":4},"S Anirudha":{"runs":30,"balls":12},"Harmeet Singh":{"runs":0,"balls":0},"CRD Fernando":{"runs":2,"balls":2},"SL Malinga":{"runs":1,"balls":1}},"2011":{"S Anirudha":{"runs":83,"balls":45},"M Vijay":{"runs":434,"balls":192},"SK Raina":{"runs":438,"balls":216},"MS Dhoni":{"runs":392,"balls":178},"JA Morkel":{"runs":138,"balls":67},"SB Styris":{"runs":5,"balls":2},"MS Bisla":{"runs":72,"balls":45},"JH Kallis":{"runs":424,"balls":232},"YK Pathan":{"runs":283,"balls":132},"MK Tiwary":{"runs":359,"balls":186},"EJG Morgan":{"runs":137,"balls":62},"G Gambhir":{"runs":378,"balls":206},"LR Shukla":{"runs":14,"balls":7},"Iqbal Abdulla":{"runs":15,"balls":9},"R Bhatia":{"runs":25,"balls":16},"S Dhawan":{"runs":400,"balls":205},"IR Jaggi":{"runs":28,"balls":16},"KC Sangakkara":{"runs":358,"balls":185},"B Chipli":{"runs":207,"balls":110},"JP Duminy":{"runs":205,"balls":125},"DT Christian":{"runs":190,"balls":110},"DB Ravi Teja":{"runs":183,"balls":98},"DW Steyn":{"runs":36,"balls":22},"A Mishra":{"runs":68,"balls":33},"I Sharma":{"runs":4,"balls":4},"AG Paunikar":{"runs":49,"balls":20},"R Dravid":{"runs":343,"balls":176},"J Botha":{"runs":230,"balls":134},"LRPL Taylor":{"runs":181,"balls":91},"BB McCullum":{"runs":357,"balls":159},"VVS Laxman":{"runs":44,"balls":21},"DPMD Jayawardene":{"runs":299,"balls":152},"BJ Hodge":{"runs":285,"balls":142},"RA Jadeja":{"runs":283,"balls":142},"RV Gomez":{"runs":46,"balls":25},"PA Patel":{"runs":202,"balls":105},"MA Agarwal":{"runs":141,"balls":67},"TM Dilshan":{"runs":226,"balls":104},"V Kohli":{"runs":557,"balls":280},"AB de Villiers":{"runs":312,"balls":160},"SS Tiwary":{"runs":187,"balls":110},"AUK Pathan":{"runs":33,"balls":8},"DA Warner":{"runs":324,"balls":147},"V Sehwag":{"runs":424,"balls":160},"UBT Chand":{"runs":2,"balls":2},"AJ Finch":{"runs":47,"balls":21},"NV Ojha":{"runs":160,"balls":68},"Y Venugopal Rao":{"runs":336,"balls":166},"IK Pathan":{"runs":150,"balls":80},"RE van der Merwe":{"runs":14,"balls":11},"M Morkel":{"runs":40,"balls":17},"UT Yadav":{"runs":1,"balls":1},"AB Dinda":{"runs":0,"balls":0},"DJ Jacobs":{"runs":92,"balls":39},"SR Tendulkar":{"runs":553,"balls":294},"AT Rayudu":{"runs":395,"balls":207},"RG Sharma":{"runs":372,"balls":194},"AC Gilchrist":{"runs":383,"balls":153},"SE Marsh":{"runs":504,"balls":228},"PC Valthaty":{"runs":463,"balls":178},"KD Karthik":{"runs":282,"balls":138},"AM Nayar":{"runs":61,"balls":31},"Sunny Singh":{"runs":43,"balls":19},"R McLaren":{"runs":90,"balls":60},"PP Chawla":{"runs":48,"balls":29},"P Kumar":{"runs":27,"balls":14},"NJ Rimmington":{"runs":1,"balls":1},"GC Smith":{"runs":42,"balls":20},"M Manhas":{"runs":114,"balls":60},"JD Ryder":{"runs":292,"balls":109},"RV Uthappa":{"runs":264,"balls":121},"Yuvraj Singh":{"runs":343,"balls":155},"AL Menaria":{"runs":180,"balls":91},"AM Rahane":{"runs":120,"balls":65},"S Badrinath":{"runs":396,"balls":212},"R Vinay Kumar":{"runs":50,"balls":31},"S Sreesanth":{"runs":1,"balls":1},"RP Singh":{"runs":2,"balls":2},"MD Mishra":{"runs":67,"balls":36},"WD Parnell":{"runs":37,"balls":22},"R Sharma":{"runs":24,"balls":10},"S Sohal":{"runs":249,"balls":108},"Z Khan":{"runs":21,"balls":12},"CA Pujara":{"runs":34,"balls":21},"JJ van der Wath":{"runs":18,"balls":9},"R Ninan":{"runs":3,"balls":3},"DL Vettori":{"runs":23,"balls":15},"S Aravind":{"runs":13,"balls":7},"SR Watson":{"runs":330,"balls":137},"MEK Hussey":{"runs":492,"balls":273},"MS Gony":{"runs":0,"balls":0},"MS Wade":{"runs":22,"balls":18},"JR Hopes":{"runs":196,"balls":103},"FY Fazal":{"runs":19,"balls":9},"AS Raut":{"runs":60,"balls":36},"SK Warne":{"runs":10,"balls":7},"A Singh":{"runs":1,"balls":1},"SW Tait":{"runs":10,"balls":7},"SK Trivedi":{"runs":0,"balls":0},"CL White":{"runs":104,"balls":66},"Y Nagar":{"runs":111,"balls":55},"TD Paine":{"runs":10,"balls":10},"M Kartik":{"runs":12,"balls":9},"SB Wagh":{"runs":2,"balls":1},"AC Thomas":{"runs":1,"balls":1},"JEC Franklin":{"runs":107,"balls":56},"A Symonds":{"runs":135,"balls":82},"KM Jadhav":{"runs":18,"balls":14},"RR Powar":{"runs":11,"balls":8},"Shakib Al Hasan":{"runs":29,"balls":15},"B Lee":{"runs":5,"balls":5},"L Balaji":{"runs":4,"balls":2},"SA Asnodkar":{"runs":9,"balls":5},"STR Binny":{"runs":37,"balls":21},"DH Yagnik":{"runs":16,"balls":11},"R Sathish":{"runs":25,"balls":17},"KA Pollard":{"runs":146,"balls":74},"R Ashwin":{"runs":2,"balls":2},"Joginder Sharma":{"runs":0,"balls":0},"S Randiv":{"runs":2,"balls":1},"DE Bollinger":{"runs":0,"balls":0},"BJ Haddin":{"runs":18,"balls":6},"CH Gayle":{"runs":608,"balls":208},"DJ Hussey":{"runs":64,"balls":35},"RJ Harris":{"runs":31,"balls":20},"NLTC Perera":{"runs":23,"balls":10},"M Muralitharan":{"runs":5,"balls":4},"MK Pandey":{"runs":246,"balls":124},"NL McCullum":{"runs":26,"balls":15},"JE Taylor":{"runs":3,"balls":2},"A Mithun":{"runs":27,"balls":12},"J Syed Mohammad":{"runs":15,"balls":9},"MR Marsh":{"runs":50,"balls":26},"SP Goswami":{"runs":29,"balls":13},"RN ten Doeschate":{"runs":107,"balls":50},"TR Birt":{"runs":75,"balls":32},"Harbhajan Singh":{"runs":103,"balls":41},"SL Malinga":{"runs":8,"balls":3},"AG Murtaza":{"runs":2,"balls":2},"M Kaif":{"runs":41,"balls":18},"Harpreet Singh":{"runs":14,"balls":13},"M Klinger":{"runs":73,"balls":42},"B Akhil":{"runs":13,"balls":6},"Bipul Sharma":{"runs":23,"balls":15},"AC Blizzard":{"runs":120,"balls":43},"TL Suman":{"runs":65,"balls":24},"AA Jhunjhunwala":{"runs":10,"balls":4},"MV Boucher":{"runs":6,"balls":4},"I Malhotra":{"runs":7,"balls":4},"L Ablish":{"runs":0,"balls":0},"CA Ingram":{"runs":21,"balls":14},"AB Agarkar":{"runs":7,"balls":4},"S Nadeem":{"runs":0,"balls":0},"P Parameswaran":{"runs":1,"balls":1},"Mandeep Singh":{"runs":47,"balls":27},"SD Chitnis":{"runs":9,"balls":6},"SJ Srivastava":{"runs":4,"balls":3},"CJ Ferguson":{"runs":48,"balls":28},"SC Ganguly":{"runs":50,"balls":28},"DS Kulkarni":{"runs":2,"balls":2},"MM Patel":{"runs":0,"balls":0},"AB McDonald":{"runs":8,"balls":5},"OA Shah":{"runs":26,"balls":12},"LA Pomersbach":{"runs":51,"balls":24},"KB Arun Karthik":{"runs":7,"balls":4},"MJ Lumb":{"runs":0,"balls":0},"S Sriram":{"runs":4,"balls":3},"VR Aaron":{"runs":0,"balls":0},"PR Shah":{"runs":5,"balls":2},"JDP Oram":{"runs":0,"balls":0},"AA Chavan":{"runs":1,"balls":1},"ND Doshi":{"runs":0,"balls":0},"B Kumar":{"runs":1,"balls":1},"CK Langeveldt":{"runs":8,"balls":3},"WP Saha":{"runs":68,"balls":39},"Y Gnaneswara Rao":{"runs":19,"balls":9},"S Rana":{"runs":18,"balls":11},"BA Bhatt":{"runs":0,"balls":0},"DJ Bravo":{"runs":11,"balls":3},"AN Ahmed":{"runs":18,"balls":8}},"2012":{"F du Plessis":{"runs":398,"balls":199},"M Vijay":{"runs":336,"balls":147},"SK Raina":{"runs":441,"balls":210},"DJ Bravo":{"runs":371,"balls":177},"JA Morkel":{"runs":107,"balls":50},"S Badrinath":{"runs":196,"balls":106},"MS Dhoni":{"runs":357,"balls":195},"RA Jadeja":{"runs":191,"balls":97},"R Ashwin":{"runs":18,"balls":10},"SB Jakati":{"runs":7,"balls":7},"DE Bollinger":{"runs":3,"balls":3},"RE Levi":{"runs":83,"balls":33},"SR Tendulkar":{"runs":324,"balls":167},"RG Sharma":{"runs":433,"balls":211},"AT Rayudu":{"runs":333,"balls":175},"JEC Franklin":{"runs":220,"balls":129},"BB McCullum":{"runs":289,"balls":149},"JH Kallis":{"runs":409,"balls":239},"G Gambhir":{"runs":590,"balls":280},"MK Tiwary":{"runs":260,"balls":158},"YK Pathan":{"runs":194,"balls":112},"DB Das":{"runs":126,"balls":61},"LR Shukla":{"runs":75,"balls":34},"R Bhatia":{"runs":35,"balls":21},"B Lee":{"runs":42,"balls":15},"Iqbal Abdulla":{"runs":2,"balls":2},"AJ Finch":{"runs":55,"balls":28},"V Sehwag":{"runs":495,"balls":210},"IK Pathan":{"runs":176,"balls":91},"GJ Maxwell":{"runs":6,"balls":5},"MK Pandey":{"runs":143,"balls":67},"WD Parnell":{"runs":19,"balls":13},"SC Ganguly":{"runs":268,"balls":148},"RV Uthappa":{"runs":405,"balls":210},"CJ Ferguson":{"runs":50,"balls":33},"SPD Smith":{"runs":362,"balls":197},"MN Samuels":{"runs":124,"balls":69},"B Kumar":{"runs":40,"balls":24},"M Kartik":{"runs":26,"balls":17},"KD Karthik":{"runs":238,"balls":126},"SA Yadav":{"runs":0,"balls":0},"KA Pollard":{"runs":220,"balls":97},"Harbhajan Singh":{"runs":108,"balls":48},"SL Malinga":{"runs":55,"balls":28},"PP Ojha":{"runs":4,"balls":4},"MM Patel":{"runs":2,"balls":2},"R Dravid":{"runs":462,"balls":226},"AM Rahane":{"runs":560,"balls":273},"AL Menaria":{"runs":220,"balls":123},"BJ Hodge":{"runs":245,"balls":124},"OA Shah":{"runs":340,"balls":163},"KK Cooper":{"runs":38,"balls":13},"AC Gilchrist":{"runs":172,"balls":81},"PC Valthaty":{"runs":30,"balls":16},"SE Marsh":{"runs":336,"balls":167},"AM Nayar":{"runs":45,"balls":31},"Mandeep Singh":{"runs":432,"balls":206},"DJ Hussey":{"runs":396,"balls":200},"Bipul Sharma":{"runs":72,"balls":35},"PP Chawla":{"runs":106,"balls":55},"JP Faulkner":{"runs":14,"balls":11},"P Kumar":{"runs":35,"balls":18},"Harmeet Singh":{"runs":15,"balls":5},"AB McDonald":{"runs":47,"balls":19},"CA Pujara":{"runs":17,"balls":7},"V Kohli":{"runs":364,"balls":197},"AB de Villiers":{"runs":319,"balls":144},"SS Tiwary":{"runs":191,"balls":110},"MA Agarwal":{"runs":225,"balls":88},"DL Vettori":{"runs":31,"balls":17},"R Vinay Kumar":{"runs":68,"balls":42},"HV Patel":{"runs":15,"balls":12},"NV Ojha":{"runs":255,"balls":113},"Y Venugopal Rao":{"runs":132,"balls":76},"Y Nagar":{"runs":153,"balls":89},"DAJ Bracewell":{"runs":12,"balls":8},"M Morkel":{"runs":3,"balls":3},"DJ Harris":{"runs":111,"balls":51},"S Dhawan":{"runs":569,"balls":276},"PA Patel":{"runs":194,"balls":101},"CL White":{"runs":479,"balls":231},"B Chipli":{"runs":37,"balls":17},"DT Christian":{"runs":145,"balls":85},"MS Gony":{"runs":4,"balls":4},"DB Ravi Teja":{"runs":4,"balls":1},"DW Steyn":{"runs":19,"balls":10},"Ankit Sharma":{"runs":18,"balls":8},"SP Goswami":{"runs":69,"balls":47},"SP Narine":{"runs":9,"balls":3},"JD Ryder":{"runs":256,"balls":134},"R Sharma":{"runs":2,"balls":1},"AD Mascarenhas":{"runs":14,"balls":9},"KC Sangakkara":{"runs":200,"balls":106},"A Mishra":{"runs":16,"balls":12},"TL Suman":{"runs":15,"balls":7},"MS Bisla":{"runs":213,"balls":101},"RN ten Doeschate":{"runs":21,"balls":12},"Shakib Al Hasan":{"runs":91,"balls":50},"CH Gayle":{"runs":733,"balls":283},"Z Khan":{"runs":12,"balls":8},"KP Pietersen":{"runs":305,"balls":129},"DPMD Jayawardene":{"runs":335,"balls":182},"J Botha":{"runs":58,"balls":35},"AA Chavan":{"runs":11,"balls":5},"A Singh":{"runs":0,"balls":0},"SK Trivedi":{"runs":5,"balls":3},"GB Hogg":{"runs":15,"balls":11},"RR Bhatkal":{"runs":0,"balls":0},"AD Mathews":{"runs":127,"balls":79},"M Manhas":{"runs":120,"balls":63},"A Nehra":{"runs":11,"balls":7},"AB Dinda":{"runs":2,"balls":2},"JP Duminy":{"runs":244,"balls":133},"AA Jhunjhunwala":{"runs":24,"balls":14},"LRPL Taylor":{"runs":197,"balls":110},"P Dogra":{"runs":15,"balls":13},"BA Bhatt":{"runs":6,"balls":1},"M Kaif":{"runs":14,"balls":11},"S Aravind":{"runs":14,"balls":5},"M Muralitharan":{"runs":6,"balls":3},"DJ Jacobs":{"runs":0,"balls":0},"CJ McKay":{"runs":8,"balls":7},"RP Singh":{"runs":6,"balls":6},"DH Yagnik":{"runs":25,"balls":9},"TM Dilshan":{"runs":285,"balls":144},"DA Warner":{"runs":256,"balls":87},"N Saini":{"runs":140,"balls":75},"DA Miller":{"runs":98,"balls":52},"Azhar Mahmood":{"runs":186,"balls":89},"P Negi":{"runs":36,"balls":18},"NLTC Perera":{"runs":4,"balls":4},"IR Jaggi":{"runs":15,"balls":12},"STR Binny":{"runs":90,"balls":42},"RJ Peterson":{"runs":32,"balls":17},"AC Thomas":{"runs":19,"balls":10},"AC Blizzard":{"runs":0,"balls":0},"WP Saha":{"runs":6,"balls":6},"KMDN Kulasekara":{"runs":5,"balls":2},"A Ashish Reddy":{"runs":35,"balls":17},"V Pratap Singh":{"runs":0,"balls":0},"MEK Hussey":{"runs":261,"balls":124},"BB Samantray":{"runs":2,"balls":2},"MJ Clarke":{"runs":98,"balls":53},"SR Watson":{"runs":255,"balls":101},"AUK Pathan":{"runs":6,"balls":4},"Gurkeerat Singh":{"runs":86,"balls":37},"RJ Harris":{"runs":18,"balls":8},"DR Smith":{"runs":157,"balls":62},"J Syed Mohammad":{"runs":4,"balls":1},"S Nadeem":{"runs":0,"balls":0},"VR Aaron":{"runs":1,"balls":1},"AP Majumdar":{"runs":87,"balls":49},"SD Chitnis":{"runs":66,"balls":36},"PA Reddy":{"runs":73,"balls":38},"J Theron":{"runs":7,"balls":4},"S Anirudha":{"runs":19,"balls":6},"MD Mishra":{"runs":4,"balls":1},"K Upadhyay":{"runs":11,"balls":5},"HH Gibbs":{"runs":81,"balls":40},"P Awana":{"runs":4,"balls":4},"UBT Chand":{"runs":36,"balls":14},"AD Russell":{"runs":47,"balls":20},"UT Yadav":{"runs":2,"balls":2},"A Chandila":{"runs":0,"balls":0},"CA Lynn":{"runs":6,"balls":3},"Harpreet Singh":{"runs":6,"balls":5},"AG Murtaza":{"runs":3,"balls":3},"P Parameswaran":{"runs":0,"balls":0},"DS Kulkarni":{"runs":10,"balls":4},"Sunny Gupta":{"runs":0,"balls":0}},"2013":{"UBT Chand":{"runs":158,"balls":78},"DPMD Jayawardene":{"runs":331,"balls":163},"DA Warner":{"runs":410,"balls":197},"MC Juneja":{"runs":125,"balls":80},"NV Ojha":{"runs":9,"balls":6},"J Botha":{"runs":43,"balls":19},"IK Pathan":{"runs":153,"balls":93},"AD Russell":{"runs":11,"balls":8},"S Nadeem":{"runs":14,"balls":8},"A Nehra":{"runs":1,"balls":1},"MS Bisla":{"runs":255,"balls":110},"G Gambhir":{"runs":406,"balls":198},"JH Kallis":{"runs":311,"balls":175},"MK Tiwary":{"runs":146,"balls":85},"EJG Morgan":{"runs":307,"balls":138},"YK Pathan":{"runs":332,"balls":151},"CH Gayle":{"runs":720,"balls":269},"TM Dilshan":{"runs":76,"balls":36},"V Kohli":{"runs":639,"balls":295},"MA Agarwal":{"runs":67,"balls":31},"DT Christian":{"runs":6,"balls":5},"KK Nair":{"runs":9,"balls":4},"KB Arun Karthik":{"runs":41,"balls":22},"RT Ponting":{"runs":52,"balls":33},"SR Tendulkar":{"runs":287,"balls":132},"KD Karthik":{"runs":510,"balls":250},"RG Sharma":{"runs":538,"balls":274},"AT Rayudu":{"runs":265,"balls":159},"Harbhajan Singh":{"runs":116,"balls":52},"KA Pollard":{"runs":420,"balls":177},"PA Reddy":{"runs":91,"balls":57},"PA Patel":{"runs":294,"balls":149},"KC Sangakkara":{"runs":120,"balls":75},"CL White":{"runs":226,"balls":116},"NLTC Perera":{"runs":235,"balls":113},"GH Vihari":{"runs":241,"balls":161},"A Ashish Reddy":{"runs":125,"balls":65},"DB Ravi Teja":{"runs":14,"balls":13},"RV Uthappa":{"runs":434,"balls":216},"MK Pandey":{"runs":136,"balls":80},"MN Samuels":{"runs":8,"balls":5},"Yuvraj Singh":{"runs":238,"balls":104},"LRPL Taylor":{"runs":63,"balls":42},"AM Nayar":{"runs":66,"balls":45},"MR Marsh":{"runs":140,"balls":67},"AD Mathews":{"runs":172,"balls":96},"B Kumar":{"runs":52,"balls":32},"R Sharma":{"runs":11,"balls":7},"AB Dinda":{"runs":9,"balls":6},"MDKJ Perera":{"runs":14,"balls":5},"AM Rahane":{"runs":488,"balls":275},"R Dravid":{"runs":471,"balls":225},"STR Binny":{"runs":293,"balls":135},"BJ Hodge":{"runs":293,"balls":149},"AL Menaria":{"runs":1,"balls":1},"KK Cooper":{"runs":39,"balls":13},"R Shukla":{"runs":1,"balls":1},"DR Smith":{"runs":418,"balls":178},"MEK Hussey":{"runs":733,"balls":363},"M Vijay":{"runs":312,"balls":159},"SK Raina":{"runs":548,"balls":270},"DJ Bravo":{"runs":121,"balls":59},"S Badrinath":{"runs":124,"balls":77},"MS Dhoni":{"runs":461,"balls":204},"RA Jadeja":{"runs":201,"balls":100},"R Ashwin":{"runs":35,"balls":22},"B Laughlin":{"runs":4,"balls":4},"AS Rajpoot":{"runs":2,"balls":1},"TL Suman":{"runs":52,"balls":27},"AC Gilchrist":{"runs":294,"balls":127},"Mandeep Singh":{"runs":260,"balls":133},"M Vohra":{"runs":161,"balls":74},"DJ Hussey":{"runs":235,"balls":131},"MC Henriques":{"runs":165,"balls":79},"R Vinay Kumar":{"runs":70,"balls":29},"M Kartik":{"runs":2,"balls":2},"JD Unadkat":{"runs":2,"balls":2},"DW Steyn":{"runs":53,"balls":22},"SR Watson":{"runs":543,"balls":237},"DH Yagnik":{"runs":125,"balls":56},"S Sreesanth":{"runs":1,"balls":1},"LR Shukla":{"runs":3,"balls":3},"R Bhatia":{"runs":99,"balls":48},"B Lee":{"runs":21,"balls":7},"Mohammed Shami":{"runs":5,"balls":4},"SP Narine":{"runs":21,"balls":11},"BMAJ Mendis":{"runs":23,"balls":19},"KM Jadhav":{"runs":152,"balls":89},"M Morkel":{"runs":57,"balls":22},"UT Yadav":{"runs":38,"balls":22},"Gurkeerat Singh":{"runs":108,"balls":55},"Azhar Mahmood":{"runs":196,"balls":96},"R Sathish":{"runs":109,"balls":49},"PP Chawla":{"runs":64,"balls":31},"RJ Harris":{"runs":2,"balls":2},"P Kumar":{"runs":47,"balls":20},"P Awana":{"runs":1,"balls":1},"R McLaren":{"runs":3,"balls":2},"PJ Sangwan":{"runs":4,"balls":1},"AB de Villiers":{"runs":373,"balls":164},"JP Faulkner":{"runs":57,"balls":29},"AJ Finch":{"runs":456,"balls":189},"V Sehwag":{"runs":295,"balls":130},"A Mishra":{"runs":89,"balls":55},"R Rampaul":{"runs":38,"balls":19},"CH Morris":{"runs":14,"balls":10},"KV Sharma":{"runs":85,"balls":48},"SV Samson":{"runs":206,"balls":112},"SPD Smith":{"runs":159,"balls":84},"S Anirudha":{"runs":0,"balls":0},"JA Morkel":{"runs":46,"balls":23},"DA Miller":{"runs":418,"balls":188},"MS Gony":{"runs":45,"balls":15},"DB Das":{"runs":75,"balls":34},"SMSM Senanayake":{"runs":10,"balls":9},"BJ Rohrer":{"runs":193,"balls":89},"KL Rahul":{"runs":20,"balls":7},"AB McDonald":{"runs":0,"balls":0},"J Syed Mohammad":{"runs":10,"balls":6},"Q de Kock":{"runs":6,"balls":3},"BB Samantray":{"runs":123,"balls":66},"R Dhawan":{"runs":21,"balls":10},"MG Johnson":{"runs":39,"balls":21},"SL Malinga":{"runs":9,"balls":5},"PP Ojha":{"runs":2,"balls":2},"AB Agarkar":{"runs":12,"balls":11},"PC Valthaty":{"runs":6,"balls":5},"AD Mascarenhas":{"runs":5,"balls":4},"L Balaji":{"runs":9,"balls":5},"A Chandila":{"runs":4,"balls":4},"SW Tait":{"runs":1,"balls":1},"SK Trivedi":{"runs":3,"balls":2},"SS Tiwary":{"runs":109,"balls":66},"LJ Wright":{"runs":106,"balls":41},"M Manhas":{"runs":13,"balls":9},"AG Murtaza":{"runs":5,"balls":2},"IC Pandey":{"runs":0,"balls":0},"SE Marsh":{"runs":300,"balls":152},"CM Gautam":{"runs":44,"balls":23},"S Dhawan":{"runs":311,"balls":156},"X Thalaivan Sargunam":{"runs":10,"balls":8},"DJG Sammy":{"runs":174,"balls":81},"WP Saha":{"runs":70,"balls":30},"BB McCullum":{"runs":6,"balls":3},"A Mukund":{"runs":19,"balls":14},"OA Shah":{"runs":25,"balls":18},"KW Richardson":{"runs":34,"balls":20},"S Narwal":{"runs":23,"balls":10},"LA Pomersbach":{"runs":58,"balls":29},"BAW Mendis":{"runs":2,"balls":2},"CA Pujara":{"runs":92,"balls":46},"MM Sharma":{"runs":0,"balls":0},"Iqbal Abdulla":{"runs":8,"balls":8},"RN ten Doeschate":{"runs":85,"balls":45},"UA Birla":{"runs":7,"balls":4},"M Rawat":{"runs":5,"balls":5},"WD Parnell":{"runs":5,"balls":5},"Parvez Rasool":{"runs":5,"balls":5},"K Upadhyay":{"runs":1,"balls":1},"GJ Maxwell":{"runs":36,"balls":12},"Harmeet Singh":{"runs":3,"balls":2},"Sandeep Sharma":{"runs":0,"balls":0},"A Mithun":{"runs":2,"balls":1},"RE van der Merwe":{"runs":22,"balls":14},"S Kaul":{"runs":7,"balls":4},"AP Tare":{"runs":123,"balls":50},"Sachin Baby":{"runs":3,"balls":2},"PV Tambe":{"runs":3,"balls":3},"NM Coulter-Nile":{"runs":9,"balls":4},"RV Gomez":{"runs":4,"balls":1},"B Chipli":{"runs":16,"balls":8},"P Dogra":{"runs":5,"balls":4}},"2014":{"G Gambhir":{"runs":335,"balls":177},"JH Kallis":{"runs":151,"balls":78},"MK Pandey":{"runs":409,"balls":217},"RV Uthappa":{"runs":660,"balls":314},"YK Pathan":{"runs":268,"balls":112},"Shakib Al Hasan":{"runs":229,"balls":113},"SA Yadav":{"runs":164,"balls":75},"MEK Hussey":{"runs":209,"balls":108},"AP Tare":{"runs":126,"balls":55},"AT Rayudu":{"runs":361,"balls":198},"RG Sharma":{"runs":390,"balls":196},"KA Pollard":{"runs":273,"balls":133},"CJ Anderson":{"runs":265,"balls":111},"Harbhajan Singh":{"runs":28,"balls":11},"CM Gautam":{"runs":121,"balls":48},"MA Agarwal":{"runs":115,"balls":54},"M Vijay":{"runs":207,"balls":107},"KD Karthik":{"runs":325,"balls":165},"MK Tiwary":{"runs":152,"balls":81},"JP Duminy":{"runs":410,"balls":219},"LRPL Taylor":{"runs":59,"balls":38},"PA Patel":{"runs":205,"balls":96},"NJ Maddinson":{"runs":16,"balls":5},"V Kohli":{"runs":359,"balls":187},"Yuvraj Singh":{"runs":376,"balls":155},"DR Smith":{"runs":566,"balls":228},"BB McCullum":{"runs":405,"balls":196},"SK Raina":{"runs":523,"balls":238},"MS Dhoni":{"runs":371,"balls":173},"DJ Bravo":{"runs":8,"balls":3},"CA Pujara":{"runs":125,"balls":66},"V Sehwag":{"runs":455,"balls":179},"GJ Maxwell":{"runs":552,"balls":203},"AR Patel":{"runs":62,"balls":37},"DA Miller":{"runs":446,"balls":208},"GJ Bailey":{"runs":257,"balls":130},"AJ Finch":{"runs":309,"balls":153},"DA Warner":{"runs":528,"balls":256},"S Dhawan":{"runs":377,"balls":178},"KL Rahul":{"runs":166,"balls":104},"DJG Sammy":{"runs":108,"balls":49},"Y Venugopal Rao":{"runs":71,"balls":40},"KV Sharma":{"runs":42,"balls":20},"AM Nayar":{"runs":43,"balls":18},"SV Samson":{"runs":339,"balls":162},"AM Rahane":{"runs":339,"balls":177},"SR Watson":{"runs":246,"balls":99},"STR Binny":{"runs":123,"balls":71},"BJ Hodge":{"runs":101,"balls":47},"R Bhatia":{"runs":67,"balls":36},"JP Faulkner":{"runs":181,"balls":70},"Z Khan":{"runs":8,"balls":3},"SL Malinga":{"runs":2,"balls":2},"PP Ojha":{"runs":4,"balls":4},"JJ Bumrah":{"runs":1,"balls":1},"AB de Villiers":{"runs":395,"balls":175},"JDS Neesham":{"runs":42,"balls":21},"SPD Smith":{"runs":152,"balls":77},"WP Saha":{"runs":362,"balls":154},"F du Plessis":{"runs":303,"balls":168},"RA Jadeja":{"runs":146,"balls":82},"M Manhas":{"runs":35,"balls":16},"R Ashwin":{"runs":45,"balls":30},"S Nadeem":{"runs":7,"balls":7},"Mohammed Shami":{"runs":3,"balls":3},"JD Unadkat":{"runs":1,"balls":1},"MG Johnson":{"runs":56,"balls":24},"IK Pathan":{"runs":55,"balls":34},"DW Steyn":{"runs":22,"balls":16},"A Mishra":{"runs":4,"balls":4},"B Kumar":{"runs":1,"balls":1},"TG Southee":{"runs":4,"balls":1},"DS Kulkarni":{"runs":35,"balls":19},"PV Tambe":{"runs":5,"balls":5},"CA Lynn":{"runs":58,"balls":28},"R Vinay Kumar":{"runs":4,"balls":3},"YV Takawale":{"runs":104,"balls":43},"JA Morkel":{"runs":45,"balls":22},"Q de Kock":{"runs":153,"balls":69},"KP Pietersen":{"runs":294,"balls":143},"S Rana":{"runs":73,"balls":38},"MA Starc":{"runs":85,"balls":49},"R Rampaul":{"runs":13,"balls":7},"AB Dinda":{"runs":4,"balls":4},"KK Nair":{"runs":330,"balls":144},"R Dhawan":{"runs":82,"balls":45},"L Balaji":{"runs":1,"balls":1},"Sandeep Sharma":{"runs":2,"balls":2},"PP Chawla":{"runs":31,"balls":13},"SP Narine":{"runs":10,"balls":9},"UT Yadav":{"runs":2,"balls":2},"M Morkel":{"runs":4,"balls":3},"KM Jadhav":{"runs":149,"balls":72},"CH Gayle":{"runs":196,"balls":77},"VR Aaron":{"runs":35,"balls":21},"MS Bisla":{"runs":3,"balls":3},"NV Ojha":{"runs":232,"balls":97},"BR Dunk":{"runs":40,"balls":16},"AD Russell":{"runs":2,"balls":2},"RR Rossouw":{"runs":39,"balls":21},"HV Patel":{"runs":13,"balls":4},"RN ten Doeschate":{"runs":52,"balls":21},"LR Shukla":{"runs":31,"balls":20},"Mandeep Singh":{"runs":24,"balls":13},"MC Henriques":{"runs":9,"balls":6},"KW Richardson":{"runs":1,"balls":1},"Shivam Sharma":{"runs":5,"balls":2},"YS Chahal":{"runs":1,"balls":1},"R Shukla":{"runs":18,"balls":12},"LMP Simmons":{"runs":394,"balls":174},"VH Zol":{"runs":29,"balls":13},"Ankit Sharma":{"runs":34,"balls":14},"DH Yagnik":{"runs":4,"balls":4},"M Vohra":{"runs":324,"balls":133},"KK Cooper":{"runs":39,"balls":15},"BCJ Cutting":{"runs":8,"balls":3},"Imran Tahir":{"runs":8,"balls":2},"S Kaul":{"runs":2,"balls":2},"DJ Hussey":{"runs":116,"balls":61},"AN Ahmed":{"runs":4,"balls":1},"UBT Chand":{"runs":2,"balls":2},"WD Parnell":{"runs":2,"balls":1},"SE Marsh":{"runs":70,"balls":28},"BE Hendricks":{"runs":0,"balls":0},"S Gopal":{"runs":11,"balls":8},"M de Lange":{"runs":1,"balls":1},"R Tewatia":{"runs":16,"balls":8},"VS Malik":{"runs":1,"balls":1},"S Anirudha":{"runs":3,"balls":3},"JO Holder":{"runs":16,"balls":5},"Karanveer Singh":{"runs":1,"balls":1},"P Kumar":{"runs":1,"balls":1},"MM Sharma":{"runs":1,"balls":1}},"2015":{"RG Sharma":{"runs":482,"balls":231},"AJ Finch":{"runs":23,"balls":10},"AP Tare":{"runs":14,"balls":10},"AT Rayudu":{"runs":281,"balls":134},"CJ Anderson":{"runs":114,"balls":46},"RV Uthappa":{"runs":364,"balls":174},"G Gambhir":{"runs":327,"balls":168},"MK Pandey":{"runs":225,"balls":115},"SA Yadav":{"runs":157,"balls":73},"YK Pathan":{"runs":312,"balls":151},"DR Smith":{"runs":399,"balls":152},"BB McCullum":{"runs":436,"balls":154},"SK Raina":{"runs":374,"balls":180},"F du Plessis":{"runs":380,"balls":213},"RA Jadeja":{"runs":132,"balls":84},"MS Dhoni":{"runs":372,"balls":182},"DJ Bravo":{"runs":195,"balls":94},"R Ashwin":{"runs":52,"balls":25},"MM Sharma":{"runs":28,"balls":12},"MA Agarwal":{"runs":213,"balls":104},"CM Gautam":{"runs":4,"balls":3},"JA Morkel":{"runs":86,"balls":44},"SS Iyer":{"runs":439,"balls":194},"KM Jadhav":{"runs":189,"balls":95},"Yuvraj Singh":{"runs":248,"balls":118},"JP Duminy":{"runs":414,"balls":207},"NM Coulter-Nile":{"runs":20,"balls":8},"A Mishra":{"runs":8,"balls":7},"Imran Tahir":{"runs":5,"balls":4},"AM Rahane":{"runs":540,"balls":273},"SV Samson":{"runs":204,"balls":97},"SPD Smith":{"runs":298,"balls":159},"KK Nair":{"runs":181,"balls":87},"STR Binny":{"runs":74,"balls":45},"JP Faulkner":{"runs":144,"balls":72},"DJ Hooda":{"runs":151,"balls":64},"CH Morris":{"runs":76,"balls":37},"V Sehwag":{"runs":99,"balls":48},"WP Saha":{"runs":249,"balls":127},"M Vijay":{"runs":251,"balls":110},"GJ Maxwell":{"runs":146,"balls":60},"AR Patel":{"runs":206,"balls":119},"DA Miller":{"runs":357,"balls":168},"GJ Bailey":{"runs":259,"balls":138},"MG Johnson":{"runs":31,"balls":20},"Anureet Singh":{"runs":18,"balls":13},"Karanveer Singh":{"runs":11,"balls":7},"DA Warner":{"runs":562,"balls":229},"S Dhawan":{"runs":353,"balls":172},"KL Rahul":{"runs":142,"balls":79},"NV Ojha":{"runs":137,"balls":71},"RS Bopara":{"runs":145,"balls":83},"KS Williamson":{"runs":31,"balls":21},"KV Sharma":{"runs":104,"balls":59},"Parvez Rasool":{"runs":2,"balls":2},"AD Russell":{"runs":326,"balls":118},"Shakib Al Hasan":{"runs":36,"balls":18},"CH Gayle":{"runs":491,"balls":177},"V Kohli":{"runs":505,"balls":247},"KD Karthik":{"runs":141,"balls":68},"Mandeep Singh":{"runs":157,"balls":67},"AB de Villiers":{"runs":513,"balls":201},"DJG Sammy":{"runs":13,"balls":13},"SA Abbott":{"runs":15,"balls":6},"HV Patel":{"runs":19,"balls":7},"AN Ahmed":{"runs":10,"balls":4},"AD Mathews":{"runs":144,"balls":70},"TG Southee":{"runs":13,"balls":8},"R Dhawan":{"runs":36,"balls":18},"KA Pollard":{"runs":419,"balls":174},"J Suchith":{"runs":48,"balls":21},"Harbhajan Singh":{"runs":117,"balls":40},"VR Aaron":{"runs":6,"balls":1},"YS Chahal":{"runs":1,"balls":1},"PA Patel":{"runs":339,"balls":150},"UBT Chand":{"runs":102,"balls":48},"S Gopal":{"runs":1,"balls":1},"P Negi":{"runs":116,"balls":51},"A Nehra":{"runs":1,"balls":1},"RG More":{"runs":2,"balls":2},"EJG Morgan":{"runs":187,"balls":88},"A Ashish Reddy":{"runs":73,"balls":33},"LMP Simmons":{"runs":540,"balls":240},"R Vinay Kumar":{"runs":0,"balls":0},"P Kumar":{"runs":17,"balls":13},"NLTC Perera":{"runs":12,"balls":7},"Gurkeerat Singh":{"runs":35,"balls":21},"RN ten Doeschate":{"runs":61,"balls":30},"PP Chawla":{"runs":54,"balls":27},"SR Watson":{"runs":347,"balls":151},"HH Pandya":{"runs":112,"balls":42},"MS Bisla":{"runs":37,"balls":12},"RR Rossouw":{"runs":14,"balls":5},"D Wiese":{"runs":122,"balls":61},"Iqbal Abdulla":{"runs":20,"balls":8},"MK Tiwary":{"runs":57,"balls":28},"SE Marsh":{"runs":93,"balls":40},"MC Henriques":{"runs":287,"balls":145},"SN Khan":{"runs":111,"balls":56},"MA Starc":{"runs":11,"balls":8},"MJ McClenaghan":{"runs":13,"balls":3},"SL Malinga":{"runs":6,"balls":3},"DS Kulkarni":{"runs":4,"balls":4},"PV Tambe":{"runs":3,"balls":3},"GH Vihari":{"runs":39,"balls":20},"DW Steyn":{"runs":20,"balls":10},"B Kumar":{"runs":17,"balls":5},"Sandeep Sharma":{"runs":9,"balls":6},"S Nadeem":{"runs":2,"balls":2},"DJ Muthuswami":{"runs":1,"balls":1},"M Vohra":{"runs":82,"balls":38},"J Botha":{"runs":31,"balls":11},"SS Tiwary":{"runs":109,"balls":51},"PJ Cummins":{"runs":0,"balls":0},"UT Yadav":{"runs":29,"balls":9},"GB Hogg":{"runs":7,"balls":6},"SN Thakur":{"runs":7,"balls":4},"J Theron":{"runs":1,"balls":1},"NJ Maddinson":{"runs":4,"balls":1},"Bipul Sharma":{"runs":1,"balls":1},"SP Narine":{"runs":0,"balls":0},"Q de Kock":{"runs":122,"balls":47},"R Bhatia":{"runs":0,"balls":0},"Ankit Sharma":{"runs":7,"balls":4},"BE Hendricks":{"runs":1,"balls":1},"MEK Hussey":{"runs":77,"balls":43},"Azhar Mahmood":{"runs":6,"balls":2},"M Morkel":{"runs":4,"balls":3},"S Aravind":{"runs":0,"balls":0}},"2016":{"LMP Simmons":{"runs":8,"balls":3},"RG Sharma":{"runs":489,"balls":239},"HH Pandya":{"runs":44,"balls":30},"JC Buttler":{"runs":255,"balls":117},"AT Rayudu":{"runs":334,"balls":177},"KA Pollard":{"runs":208,"balls":82},"S Gopal":{"runs":2,"balls":2},"Harbhajan Singh":{"runs":92,"balls":44},"R Vinay Kumar":{"runs":13,"balls":7},"MJ McClenaghan":{"runs":34,"balls":13},"AM Rahane":{"runs":480,"balls":247},"F du Plessis":{"runs":206,"balls":99},"KP Pietersen":{"runs":73,"balls":40},"MA Agarwal":{"runs":27,"balls":13},"Q de Kock":{"runs":445,"balls":203},"SS Iyer":{"runs":30,"balls":18},"KK Nair":{"runs":357,"balls":186},"SV Samson":{"runs":291,"balls":167},"P Negi":{"runs":57,"balls":32},"CR Brathwaite":{"runs":83,"balls":23},"CH Morris":{"runs":195,"balls":78},"NM Coulter-Nile":{"runs":9,"balls":6},"A Mishra":{"runs":4,"balls":4},"Z Khan":{"runs":6,"balls":3},"RV Uthappa":{"runs":394,"balls":193},"G Gambhir":{"runs":501,"balls":275},"MK Pandey":{"runs":248,"balls":136},"M Vijay":{"runs":453,"balls":224},"M Vohra":{"runs":161,"balls":73},"DA Miller":{"runs":161,"balls":91},"GJ Maxwell":{"runs":179,"balls":81},"WP Saha":{"runs":270,"balls":150},"MP Stoinis":{"runs":146,"balls":73},"AR Patel":{"runs":111,"balls":51},"AJ Finch":{"runs":393,"balls":186},"BB McCullum":{"runs":354,"balls":150},"SK Raina":{"runs":399,"balls":210},"KD Karthik":{"runs":335,"balls":178},"RA Jadeja":{"runs":191,"balls":112},"Ishan Kishan":{"runs":42,"balls":24},"DJ Bravo":{"runs":99,"balls":53},"CH Gayle":{"runs":227,"balls":69},"V Kohli":{"runs":973,"balls":471},"AB de Villiers":{"runs":687,"balls":303},"SR Watson":{"runs":179,"balls":74},"KM Jadhav":{"runs":42,"balls":22},"SN Khan":{"runs":66,"balls":22},"DA Warner":{"runs":848,"balls":376},"S Dhawan":{"runs":501,"balls":262},"MC Henriques":{"runs":182,"balls":96},"NV Ojha":{"runs":136,"balls":76},"DJ Hooda":{"runs":144,"balls":81},"EJG Morgan":{"runs":123,"balls":67},"A Ashish Reddy":{"runs":47,"balls":20},"KV Sharma":{"runs":36,"balls":18},"AD Russell":{"runs":188,"balls":74},"YK Pathan":{"runs":361,"balls":182},"C Munro":{"runs":30,"balls":18},"SA Yadav":{"runs":182,"balls":95},"PA Patel":{"runs":177,"balls":80},"SPD Smith":{"runs":270,"balls":125},"MS Dhoni":{"runs":284,"balls":138},"MR Marsh":{"runs":7,"balls":5},"R Bhatia":{"runs":34,"balls":17},"SE Marsh":{"runs":159,"balls":89},"MG Johnson":{"runs":5,"balls":4},"MM Sharma":{"runs":32,"balls":16},"P Sahu":{"runs":19,"balls":9},"Sandeep Sharma":{"runs":8,"balls":8},"B Kumar":{"runs":43,"balls":18},"KH Pandya":{"runs":237,"balls":89},"TG Southee":{"runs":30,"balls":14},"AD Nath":{"runs":20,"balls":14},"JP Faulkner":{"runs":77,"balls":45},"P Kumar":{"runs":24,"balls":14},"DS Kulkarni":{"runs":27,"balls":12},"NLTC Perera":{"runs":150,"balls":63},"IK Pathan":{"runs":11,"balls":10},"R Ashwin":{"runs":41,"balls":24},"D Wiese":{"runs":5,"balls":4},"JP Duminy":{"runs":191,"balls":118},"MJ Guptill":{"runs":57,"balls":28},"KJ Abbott":{"runs":13,"balls":5},"Shakib Al Hasan":{"runs":114,"balls":64},"KL Rahul":{"runs":397,"balls":185},"TM Head":{"runs":54,"balls":28},"STR Binny":{"runs":63,"balls":24},"KW Richardson":{"runs":1,"balls":1},"DW Steyn":{"runs":1,"balls":1},"Ankit Sharma":{"runs":3,"balls":2},"M Ashwin":{"runs":0,"balls":0},"NS Naik":{"runs":23,"balls":17},"R Dhawan":{"runs":14,"balls":6},"AP Tare":{"runs":8,"balls":4},"DR Smith":{"runs":324,"balls":130},"JA Morkel":{"runs":16,"balls":6},"R Sathish":{"runs":24,"balls":14},"PP Chawla":{"runs":27,"balls":13},"UT Yadav":{"runs":9,"balls":4},"Bipul Sharma":{"runs":51,"balls":18},"RR Pant":{"runs":198,"balls":96},"CA Lynn":{"runs":25,"balls":14},"SS Tiwary":{"runs":170,"balls":89},"SW Billings":{"runs":88,"balls":45},"Mohammed Shami":{"runs":2,"balls":2},"JO Holder":{"runs":22,"balls":9},"SP Narine":{"runs":7,"balls":6},"KS Williamson":{"runs":124,"balls":78},"Sachin Baby":{"runs":119,"balls":56},"Parvez Rasool":{"runs":10,"balls":6},"Gurkeerat Singh":{"runs":113,"balls":60},"KC Cariappa":{"runs":13,"balls":8},"PSP Handscomb":{"runs":6,"balls":6},"Swapnil Singh":{"runs":0,"balls":0},"J Yadav":{"runs":6,"balls":6},"UT Khawaja":{"runs":127,"balls":62},"Yuvraj Singh":{"runs":236,"balls":99},"GJ Bailey":{"runs":84,"balls":44},"HM Amla":{"runs":157,"balls":73},"JJ Bumrah":{"runs":8,"balls":5},"F Behardien":{"runs":14,"balls":8},"BB Sran":{"runs":4,"balls":4},"A Zampa":{"runs":0,"balls":0},"N Rana":{"runs":104,"balls":41},"A Nehra":{"runs":1,"balls":1},"UBT Chand":{"runs":0,"balls":0},"PV Tambe":{"runs":7,"balls":4},"S Kaushik":{"runs":0,"balls":0},"BCJ Cutting":{"runs":65,"balls":20},"S Nadeem":{"runs":1,"balls":1},"Imran Tahir":{"runs":5,"balls":2},"M Morkel":{"runs":1,"balls":1},"ER Dwivedi":{"runs":24,"balls":8},"SB Jakati":{"runs":1,"balls":1},"Iqbal Abdulla":{"runs":37,"balls":18},"CJ Jordan":{"runs":3,"balls":2}},"2017":{"DA Warner":{"runs":641,"balls":288},"S Dhawan":{"runs":479,"balls":250},"MC Henriques":{"runs":277,"balls":146},"Yuvraj Singh":{"runs":252,"balls":112},"DJ Hooda":{"runs":78,"balls":40},"BCJ Cutting":{"runs":51,"balls":20},"CH Gayle":{"runs":200,"balls":82},"Mandeep Singh":{"runs":188,"balls":96},"TM Head":{"runs":151,"balls":80},"KM Jadhav":{"runs":267,"balls":130},"SR Watson":{"runs":71,"balls":44},"Sachin Baby":{"runs":15,"balls":8},"STR Binny":{"runs":78,"balls":41},"S Aravind":{"runs":32,"balls":21},"YS Chahal":{"runs":13,"balls":12},"TS Mills":{"runs":8,"balls":3},"A Choudhary":{"runs":25,"balls":16},"PA Patel":{"runs":395,"balls":186},"JC Buttler":{"runs":273,"balls":106},"RG Sharma":{"runs":333,"balls":175},"N Rana":{"runs":333,"balls":163},"AT Rayudu":{"runs":91,"balls":50},"KH Pandya":{"runs":243,"balls":116},"KA Pollard":{"runs":395,"balls":183},"HH Pandya":{"runs":250,"balls":106},"TG Southee":{"runs":7,"balls":2},"AM Rahane":{"runs":382,"balls":209},"MA Agarwal":{"runs":26,"balls":14},"SPD Smith":{"runs":472,"balls":267},"BA Stokes":{"runs":316,"balls":157},"MS Dhoni":{"runs":290,"balls":145},"JJ Roy":{"runs":59,"balls":25},"BB McCullum":{"runs":320,"balls":135},"SK Raina":{"runs":442,"balls":228},"AJ Finch":{"runs":300,"balls":115},"KD Karthik":{"runs":361,"balls":189},"G Gambhir":{"runs":498,"balls":254},"CA Lynn":{"runs":295,"balls":112},"MK Tiwary":{"runs":324,"balls":165},"DT Christian":{"runs":79,"balls":32},"HM Amla":{"runs":420,"balls":195},"M Vohra":{"runs":229,"balls":99},"WP Saha":{"runs":234,"balls":123},"AR Patel":{"runs":227,"balls":118},"GJ Maxwell":{"runs":310,"balls":114},"DA Miller":{"runs":83,"balls":46},"Vishnu Vinod":{"runs":19,"balls":11},"Iqbal Abdulla":{"runs":5,"balls":4},"P Negi":{"runs":144,"balls":68},"AP Tare":{"runs":18,"balls":8},"SW Billings":{"runs":138,"balls":71},"KK Nair":{"runs":281,"balls":124},"SV Samson":{"runs":386,"balls":174},"RR Pant":{"runs":366,"balls":151},"CH Morris":{"runs":154,"balls":72},"CR Brathwaite":{"runs":12,"balls":6},"PJ Cummins":{"runs":77,"balls":35},"A Mishra":{"runs":49,"balls":30},"S Nadeem":{"runs":2,"balls":2},"Z Khan":{"runs":4,"balls":4},"DR Smith":{"runs":239,"balls":97},"DS Kulkarni":{"runs":1,"balls":1},"P Kumar":{"runs":8,"balls":8},"Basil Thampi":{"runs":28,"balls":17},"RV Uthappa":{"runs":388,"balls":164},"MK Pandey":{"runs":396,"balls":225},"YK Pathan":{"runs":143,"balls":73},"SA Yadav":{"runs":105,"balls":62},"CR Woakes":{"runs":46,"balls":26},"SP Narine":{"runs":224,"balls":70},"Harbhajan Singh":{"runs":16,"balls":10},"AB de Villiers":{"runs":216,"balls":95},"CJ Anderson":{"runs":142,"balls":67},"F du Plessis":{"runs":8,"balls":5},"RA Tripathi":{"runs":391,"balls":162},"R Bhatia":{"runs":16,"balls":10},"DL Chahar":{"runs":14,"balls":4},"A Zampa":{"runs":5,"balls":2},"AB Dinda":{"runs":7,"balls":4},"Imran Tahir":{"runs":0,"balls":0},"NV Ojha":{"runs":79,"balls":45},"V Shankar":{"runs":101,"balls":55},"Rashid Khan":{"runs":11,"balls":5},"B Kumar":{"runs":4,"balls":3},"MP Stoinis":{"runs":17,"balls":12},"MM Sharma":{"runs":51,"balls":30},"VR Aaron":{"runs":4,"balls":3},"V Kohli":{"runs":308,"balls":162},"MJ McClenaghan":{"runs":16,"balls":10},"Ankit Sharma":{"runs":25,"balls":12},"SN Thakur":{"runs":0,"balls":0},"RD Chahar":{"runs":3,"balls":2},"LH Ferguson":{"runs":1,"balls":1},"C de Grandhomme":{"runs":126,"balls":61},"Bipul Sharma":{"runs":31,"balls":15},"SS Iyer":{"runs":338,"balls":162},"EJG Morgan":{"runs":65,"balls":37},"KC Cariappa":{"runs":2,"balls":2},"Sandeep Sharma":{"runs":7,"balls":6},"Ishan Kishan":{"runs":277,"balls":118},"JD Unadkat":{"runs":2,"balls":2},"AF Milne":{"runs":7,"balls":6},"S Badree":{"runs":13,"balls":11},"AD Mathews":{"runs":32,"balls":18},"Mohammed Shami":{"runs":36,"balls":13},"Mohammad Nabi":{"runs":2,"balls":1},"I Sharma":{"runs":8,"balls":5},"RA Jadeja":{"runs":158,"balls":84},"AJ Tye":{"runs":53,"balls":22},"KS Williamson":{"runs":256,"balls":118},"SE Marsh":{"runs":264,"balls":122},"Shakib Al Hasan":{"runs":1,"balls":1},"JP Faulkner":{"runs":54,"balls":34},"MG Johnson":{"runs":20,"balls":10},"K Rabada":{"runs":55,"balls":33},"AD Nath":{"runs":0,"balls":0},"NM Coulter-Nile":{"runs":14,"balls":4},"Kuldeep Yadav":{"runs":20,"balls":13},"UT Yadav":{"runs":10,"balls":9},"Washington Sundar":{"runs":9,"balls":6},"KV Sharma":{"runs":49,"balls":23},"DM Bravo":{"runs":6,"balls":3},"AR Bawne":{"runs":12,"balls":8},"SP Jackson":{"runs":38,"balls":21},"MJ Guptill":{"runs":132,"balls":51},"Anureet Singh":{"runs":15,"balls":9},"IK Pathan":{"runs":2,"balls":2},"Ankit Soni":{"runs":7,"balls":2},"JJ Bumrah":{"runs":16,"balls":9},"SL Malinga":{"runs":7,"balls":2},"PJ Sangwan":{"runs":2,"balls":2},"S Kaul":{"runs":0,"balls":0},"LMP Simmons":{"runs":137,"balls":59},"MN Samuels":{"runs":29,"balls":14},"Swapnil Singh":{"runs":12,"balls":10},"R Tewatia":{"runs":19,"balls":7},"MM Patel":{"runs":0,"balls":0},"SS Tiwary":{"runs":52,"balls":25},"TA Boult":{"runs":5,"balls":3},"CJ Jordan":{"runs":0,"balls":0},"IR Jaggi":{"runs":33,"balls":21},"PP Chawla":{"runs":2,"balls":2},"AS Rajpoot":{"runs":4,"balls":1}}}